sumnplot/__init__.py
sumnplot/_version.py
sumnplot/checks.py
sumnplot/discretisation.py
sumnplot/summary.py
sumnplot/plot/__init__.py
sumnplot/plot/matplotlib.py
sumnplot-0.3.0.dist-info/LICENSE
sumnplot-0.3.0.dist-info/WHEEL
sumnplot-0.3.0.dist-info/METADATA
sumnplot-0.3.0.dist-info/RECORD
