Metadata-Version: 2.1
Name: sumnplot
Version: 0.3.0
Summary: (Super simple) Summarisation and Plotting - sumnplot
Home-page: https://github.com/richardangell/sumnplot
Author: Richard Angell
Author-email: richardangell37@gmail.com
Requires-Python: >=3.7
Classifier: Programming Language :: Python :: 3
Classifier: License :: OSI Approved :: MIT License
Classifier: Operating System :: OS Independent
Requires-Dist: numpy>=1.18.1
Requires-Dist: pandas>=1.0.0
Requires-Dist: scikit-learn>=1.0
Requires-Dist: matplotlib>=3.1.3
Requires-Dist: Sphinx==4.5.0 ; extra == "doc"
Requires-Dist: sphinx-rtd-theme==1.0.0 ; extra == "doc"
Requires-Dist: numpydoc==1.3.1 ; extra == "doc"
Requires-Dist: pre-commit==2.19.0 ; extra == "test"
Requires-Dist: pytest==7.1.2 ; extra == "test"
Project-URL: Documentation, https://sumnplot.readthedocs.io/en/latest/
Project-URL: PyPI, https://pypi.org/project/sumnplot/
Provides-Extra: doc
Provides-Extra: test
